{
  "report_number": "2201060467",
  "report_date": "06.01.2022",
  "client_name": "Al Taiba Farms",
  "client_address": "POB: 7727\nAI Hilal Business Tower, 22nd Floor\n2201 Fujairah\nUnited Arab Emirates",
  "contact_email": "james@altaibafarms.ae",
  "sample_id": "SAMPLE 5 - SIDR - 21/AP:11",
  "product": "Honey",
  "reference_number": "PI2112300195",
  "sample_received_date": "30.12.2021",
  "analysis_start_date": "03.01.2022",
  "analysis_end_date": "06.01.2022",
  "certifications": [
    "DIN EN ISO/IEC 17025",
    "DAkkS D-PL-14171-01-00"
  ]
}